coima
