Metadata-Version: 1.0
Name: coima
Version: 0.0.2
Summary: Extremely plain and simple template engine for text files
Home-page: http://github.com/alfredodeza/coima
Author: Alfredo Deza
Author-email: alfredodeza [at] gmail [dot] com
License: MIT
Keywords: WSGI stats requests context development
Platform: UNKNOWN
Classifier: Development Status :: 4 - Beta
Classifier: Intended Audience :: Developers
Classifier: License :: OSI Approved :: MIT License
Classifier: Topic :: Software Development :: Build Tools
Classifier: Programming Language :: Python :: 2.5
Classifier: Programming Language :: Python :: 2.6
